loginform.py
loginform-1.1.1.dist-info/top_level.txt
loginform-1.1.1.dist-info/METADATA
loginform-1.1.1.dist-info/DESCRIPTION.rst
loginform-1.1.1.dist-info/metadata.json
loginform-1.1.1.dist-info/WHEEL
loginform-1.1.1.dist-info/RECORD
