Metadata-Version: 2.0
Name: loginform
Version: 1.1.1
Summary: Fill HTML login forms automatically
Home-page: http://github.com/scrapy/loginform
Author: Scrapinghub
Author-email: info@scrapinghub.com
License: BSD
Platform: Any
Classifier: Development Status :: 5 - Production/Stable
Classifier: License :: OSI Approved :: BSD License
Classifier: Operating System :: OS Independent
Classifier: Programming Language :: Python
Classifier: Programming Language :: Python :: 2
Classifier: Programming Language :: Python :: 2.7
Classifier: Programming Language :: Python :: 3
Classifier: Programming Language :: Python :: 3.3
Classifier: Programming Language :: Python :: 3.4
Classifier: Programming Language :: Python :: Implementation :: CPython
Classifier: Topic :: Internet :: WWW/HTTP
Requires-Dist: lxml
